<?xml version="1.0" encoding="UTF-8"?><?xml-model href="https://openarabicpe.github.io/OpenArabicPE_ODD/schema/tei_periodical.rng" type="application/xml" schematypens="http://relaxng.org/ns/structure/1.0"?><?xml-model href="https://openarabicpe.github.io/OpenArabicPE_ODD/schema/tei_periodical.rng" type="application/xml" schematypens="http://purl.oclc.org/dsdl/schematron"?><?xml-model href="https://openarabicpe.github.io/OpenArabicPE_ODD/schema/tei_periodical.sch" type="application/xml" schematypens="http://purl.oclc.org/dsdl/schematron"?><?xml-stylesheet type="text/xsl" href="https://openarabicpe.github.io/tei-boilerplate-arabic-editions/boilerplate/xslt/teibp_parameters.xsl"?><tei:TEI xmlns:tei="http://www.tei-c.org/ns/1.0" xmlns="http://www.tei-c.org/ns/1.0" xml:id="oclc_42900564-i_500" prev="oclc_42900564-i_499.TEIP5.xml" next="oclc_42900564-i_501.TEIP5.xml">
   <tei:teiHeader xml:lang="en">
      <tei:fileDesc>
         <tei:titleStmt>
            <title>al-Ittiḥād al-ʿUthmānī #500, 11 May 1910</title>
            <title type="sub">TEI edition</title>
            <respStmt xml:lang="en">
               <resp>TEI edition</resp>
               <persName xml:id="pers_TG">Till Grallert</persName>
            </respStmt>
         </tei:titleStmt>
         <tei:publicationStmt>
            <authority>
               <persName>Till Grallert</persName>
            </authority>
            <pubPlace>Beirut</pubPlace>
            <date when="2019">2019</date>
            <availability status="restricted">
               <licence target="http://creativecommons.org/licenses/by-sa/4.0/">Distributed under a Creative Commons Attribution-ShareAlike 4.0 International (CC BY-SA 4.0) license</licence>
            </availability>
            <idno type="url">https://github.com/openarabicpe/newspaper_al-asr-al-jadid/blob/master/tei/oclc_42900564-i_500.TEIP5.xml</idno>
         </tei:publicationStmt>
         <tei:sourceDesc>
            <tei:biblStruct xml:lang="ar">
                    <tei:monogr xml:lang="ar">
                        <title level="j" xml:lang="ar">الاتحاد العثماني</title>
                        <title level="j" xml:lang="ar-Latn-x-ijmes">al-Ittiḥād al-ʿUthmānī</title>
                        <idno type="OCLC" xml:lang="en">42900564</idno>
                        <idno type="OCLC" xml:lang="en">506290085</idno>
                        <idno type="OCLC" xml:lang="en">792755286</idno>
                        <editor xml:lang="en">
                            <persName xml:lang="ar" change="#d2e54" ref="oape:pers:787 viaf:305214837">
                                <forename change="#d2e69" xml:lang="ar">احمد</forename>
                                <forename change="#d2e69" xml:lang="ar">حسن</forename>
                                <surname change="#d2e69" xml:lang="ar">طبارة</surname>
                            </persName>
                            <persName xml:lang="ar-Latn-x-ijmes">
                                <forename change="#d2e69" xml:lang="ar-Latn-x-ijmes">Aḥmad</forename>
                                <forename change="#d2e69" xml:lang="ar-Latn-x-ijmes">Ḥasan</forename>
                                <surname change="#d2e69" xml:lang="ar-Latn-x-ijmes">Ṭabbāra</surname>
                            </persName>
                        </editor>
                        <tei:imprint xml:lang="en">
                            <publisher xml:lang="en">
                                <orgName xml:lang="ar">مطبعة الاهلية</orgName>
                                <orgName xml:lang="ar-Latn-x-ijmes">Maṭbaʿa al-Ahliyya</orgName>
                            </publisher>
                            <pubPlace xml:lang="en">
                                <placeName xml:lang="ar" ref="geon:276781" change="#d5e74">بيروت</placeName>
                                <placeName xml:lang="ar-Latn-x-ijmes" ref="geon:276781" change="#d5e74">Bayrūt</placeName>
                                <placeName xml:lang="en" ref="geon:276781" change="#d5e74">Beirut</placeName>
                                <placeName xml:lang="fr" ref="geon:276781" change="#d5e74">Beyrouth</placeName>
                            </pubPlace>
                            <tei:date when="1910-05-11" xml:lang="en">11 May 1910, Wednesday</tei:date>
                            <tei:date calendar="#cal_islamic" datingMethod="#cal_islamic" when="1910-05-11" when-custom="1328-05-01" xml:lang="ar-Latn-x-ijmes">1 Jumāda al-ulā 1328, Wednesday</tei:date>
                            <tei:date xml:lang="ar-Latn-x-ijmes" when="1910-05-11" when-custom="1326-02-28" calendar="#cal_ottomanfiscal" datingMethod="#cal_ottomanfiscal">28 Nīsān 1326, Wednesday</tei:date>
                        </tei:imprint>
                        <tei:biblScope from="2" to="2" unit="volume"/>
                        <tei:biblScope from="500" to="500" unit="issue"/>
                        <tei:biblScope from="1" to="4" unit="page"/>
                    </tei:monogr>
                </tei:biblStruct>
         </tei:sourceDesc>
      </tei:fileDesc>
      <tei:revisionDesc><change when="2019-03-07" who="#pers_TG" xml:id="d3e150" xml:lang="en">Generated a new <tei:gi xml:lang="en">front</tei:gi>based on the <tei:gi xml:lang="en">sourceDesc</tei:gi>that matches the information found in the masthead of the actual issues.</change>
         <tei:change when="2019-03-07">Created this file by automatic conversion of <tei:gi>biblStruct</tei:gi> from file:/Volumes/Dessau%20HD/BachUni/BachBibliothek/GitHub/OpenArabicPE/newspaper_al-ittihad-al-uthmani/metadata/al-ittihad-al-uthmani.TEIP5.xml.</tei:change>
      </tei:revisionDesc>
   </tei:teiHeader>
   <tei:facsimile>
      <tei:surface xml:id="facs_1">
         <tei:graphic xml:id="facs_1-g_3" url="../images/oclc_42900564-i_500-p_1.tif" mimeType="image/tiff"/>
      </tei:surface>
      <tei:surface xml:id="facs_2">
         <tei:graphic xml:id="facs_2-g_3" url="../images/oclc_42900564-i_500-p_2.tif" mimeType="image/tiff"/>
      </tei:surface>
      <tei:surface xml:id="facs_3">
         <tei:graphic xml:id="facs_3-g_3" url="../images/oclc_42900564-i_500-p_3.tif" mimeType="image/tiff"/>
      </tei:surface>
      <tei:surface xml:id="facs_4">
         <tei:graphic xml:id="facs_4-g_3" url="../images/oclc_42900564-i_501-p_0.tif" mimeType="image/tiff"/>
      </tei:surface>
   </tei:facsimile>
   <tei:text xml:lang="ar"><tei:pb ed="print" n="1" facs="#facs_1"/>
      
      <front change="#d3e150"><tei:div change="#d3e150" type="masthead"><tei:bibl><tei:biblScope unit="issue" from="500" to="500">العدد 500</tei:biblScope><tei:biblScope unit="volume" from="2" to="2">السنة الثانية</tei:biblScope><lb/><title level="j" xml:lang="ar">الاتحاد العثماني</title><lb/><lb/><placeName xml:lang="ar" ref="geon:276781" change="#d5e74">بيروت</placeName> في <tei:date calendar="#cal_islamic" datingMethod="#cal_islamic" when="1910-05-11" when-custom="1328-05-01" xml:lang="ar">١ جمادى الاولى سنة ١٣٢٨</tei:date> الموافق <tei:date xml:lang="ar" when="1910-05-11" when-custom="1326-02-28" calendar="#cal_ottomanfiscal" datingMethod="#cal_ottomanfiscal">٢٨ نيسان سنة ١٣٢٦</tei:date> و</tei:bibl></tei:div></front>
      <tei:body>
         <tei:div type="item">
            <tei:pb ed="print" n="2" facs="#facs_2"/>
            <tei:pb ed="print" n="3" facs="#facs_3"/>
            <tei:pb ed="print" n="4" facs="#facs_4"/>
         </tei:div>
      </tei:body>
   </tei:text>
</tei:TEI>